[
    {
        "inputs": [
            {
                "internalType": "address",
                "name": "_treasury",
                "type": "address"
            },
            {
                "internalType": "uint16",
                "name": "_feeBps",
                "type": "uint16"
            }
        ],
        "stateMutability": "nonpayable",
        "type": "constructor"
    },
    {
        "anonymous": false,
        "inputs": [
            {
                "indexed": true,
                "internalType": "address",
                "name": "companyOwner",
                "type": "address"
            },
            {
                "indexed": true,
                "internalType": "address",
                "name": "payrollAddress",
                "type": "address"
            },
            {
                "indexed": false,
                "internalType": "address",
                "name": "taxRecipient",
                "type": "address"
            },
            {
                "indexed": false,
                "internalType": "uint256",
                "name": "timestamp",
                "type": "uint256"
            }
        ],
        "name": "CompanyPayrollDeployed",
        "type": "event"
    },
    {
        "inputs": [
            {
                "internalType": "address",
                "name": "companyOwner",
                "type": "address"
            },
            {
                "internalType": "address",
                "name": "taxRecipient",
                "type": "address"
            }
        ],
        "name": "deployCompanyPayroll",
        "outputs": [
            {
                "internalType": "address",
                "name": "payrollAddr",
                "type": "address"
            }
        ],
        "stateMutability": "nonpayable",
        "type": "function"
    },
    {
        "inputs": [],
        "name": "getAllPayrolls",
        "outputs": [
            {
                "internalType": "address[]",
                "name": "",
                "type": "address[]"
            }
        ],
        "stateMutability": "view",
        "type": "function"
    },
    {
        "inputs": [
            {
                "internalType": "address",
                "name": "companyOwner",
                "type": "address"
            }
        ],
        "name": "getCompanyPayrolls",
        "outputs": [
            {
                "internalType": "address[]",
                "name": "",
                "type": "address[]"
            }
        ],
        "stateMutability": "view",
        "type": "function"
    },
    {
        "inputs": [
            {
                "internalType": "address",
                "name": "companyOwner",
                "type": "address"
            }
        ],
        "name": "getCompanyPayrollCount",
        "outputs": [
            {
                "internalType": "uint256",
                "name": "",
                "type": "uint256"
            }
        ],
        "stateMutability": "view",
        "type": "function"
    },
    {
        "inputs": [],
        "name": "payrollCount",
        "outputs": [
            {
                "internalType": "uint256",
                "name": "",
                "type": "uint256"
            }
        ],
        "stateMutability": "view",
        "type": "function"
    },
    {
        "inputs": [
            {
                "internalType": "address",
                "name": "payrollAddress",
                "type": "address"
            }
        ],
        "name": "isValidPayroll",
        "outputs": [
            {
                "internalType": "bool",
                "name": "",
                "type": "bool"
            }
        ],
        "stateMutability": "view",
        "type": "function"
    },
    {
        "inputs": [],
        "name": "decipherlabsFeeBps",
        "outputs": [
            {
                "internalType": "uint16",
                "name": "",
                "type": "uint16"
            }
        ],
        "stateMutability": "view",
        "type": "function"
    },
    {
        "inputs": [],
        "name": "decipherlabsTreasury",
        "outputs": [
            {
                "internalType": "address",
                "name": "",
                "type": "address"
            }
        ],
        "stateMutability": "view",
        "type": "function"
    },
    {
        "inputs": [],
        "name": "owner",
        "outputs": [
            {
                "internalType": "address",
                "name": "",
                "type": "address"
            }
        ],
        "stateMutability": "view",
        "type": "function"
    }
]